pymeteobridgesql/__init__.py
pymeteobridgesql/api.py
pymeteobridgesql/data.py
pymeteobridgesql-1.4.0.dist-info/LICENSE
pymeteobridgesql-1.4.0.dist-info/METADATA
pymeteobridgesql-1.4.0.dist-info/WHEEL
pymeteobridgesql-1.4.0.dist-info/top_level.txt
pymeteobridgesql-1.4.0.dist-info/RECORD
