Metadata-Version: 2.2
Name: pymeteobridgesql
Version: 1.4.0
Summary: Gets weather data from a MySQL table
Home-page: https://github.com/briis/pymeteobridgesql
Author: briis
Author-email: bjarne@briis.com
License: MIT
Classifier: Programming Language :: Python :: 3
Classifier: License :: OSI Approved :: MIT License
Classifier: Operating System :: OS Independent
Classifier: Development Status :: 4 - Beta
License-File: LICENSE
Dynamic: author
Dynamic: author-email
Dynamic: classifier
Dynamic: description
Dynamic: description-content-type
Dynamic: home-page
Dynamic: license
Dynamic: summary
